{
  "name": "GST ramp with long recovery",
  "description": "Same delay ramp but 30s recovery window to verify async protocols resume",
  "duration_s": 90,
  "phases": [
    {"time_s": 0, "action": "set_delay", "delay_ms": 40, "jitter_ms": 0},
    {"time_s": 10, "action": "set_delay", "delay_ms": 200, "jitter_ms": 50},
    {"time_s": 20, "action": "set_delay", "delay_ms": 500, "jitter_ms": 100},
    {"time_s": 30, "action": "set_delay", "delay_ms": 1000, "jitter_ms": 200},
    {"time_s": 40, "action": "set_delay", "delay_ms": 2000, "jitter_ms": 500},
    {"time_s": 50, "action": "set_delay", "delay_ms": 40, "jitter_ms": 0}
  ]
}
